django_ratelimiter/__init__.py
django_ratelimiter/decorator.py
django_ratelimiter/middleware.py
django_ratelimiter/py.typed
django_ratelimiter/storage.py
django_ratelimiter/types.py
django_ratelimiter/utils.py
django_ratelimiter-0.2.2.dist-info/LICENSE
django_ratelimiter-0.2.2.dist-info/METADATA
django_ratelimiter-0.2.2.dist-info/WHEEL
django_ratelimiter-0.2.2.dist-info/RECORD
