Metadata-Version: 2.1
Name: django-ratelimiter
Version: 0.2.2
Summary: Rate-limiting for django
Home-page: https://andriykohut.github.io/django-ratelimiter/
License: MIT
Keywords: rate-limit,django
Author: Andrii Kohut
Author-email: kogut.andriy@gmail.com
Requires-Python: >=3.9
Classifier: License :: OSI Approved :: MIT License
Classifier: Programming Language :: Python :: 3
Classifier: Programming Language :: Python :: 3.9
Classifier: Programming Language :: Python :: 3.10
Classifier: Programming Language :: Python :: 3.11
Classifier: Programming Language :: Python :: 3.12
Requires-Dist: django
Requires-Dist: limits (>=3.10)
Requires-Dist: typing-extensions (>=4.11.0,<5.0.0) ; python_version == "3.9"
Project-URL: Documentation, https://andriykohut.github.io/django-ratelimiter/
Project-URL: Repository, https://github.com/andriykohut/django-ratelimiter
